better_exceptions_hook/__init__.py
better_exceptions_hook-1.0.0.data/data/lib/python3.6/site-packages/better_exceptions_hook.pth
better_exceptions_hook-1.0.0.dist-info/DESCRIPTION.rst
better_exceptions_hook-1.0.0.dist-info/METADATA
better_exceptions_hook-1.0.0.dist-info/RECORD
better_exceptions_hook-1.0.0.dist-info/WHEEL
better_exceptions_hook-1.0.0.dist-info/metadata.json
better_exceptions_hook-1.0.0.dist-info/top_level.txt
