Metadata-Version: 2.0
Name: better-exceptions-hook
Version: 1.0.0
Summary: Import hook for better-exceptions
Home-page: https://github.com/paradoxxxzero/better-exceptions-hook
Author: Florian Mounier
Author-email: paradoxxx.zero@gmail.com
License: MIT
Platform: Any
Requires-Dist: better-exceptions
